nbscript/__init__.py
nbscript/_version.py
nbscript/nbscript.py
nbscript/snotebook.py
nbscript/test_nbscript.py
nbscript/test_snotebook.py
nbscript/testutil.py
nbscript-0.1.0.dist-info/LICENSE
nbscript-0.1.0.dist-info/METADATA
nbscript-0.1.0.dist-info/WHEEL
nbscript-0.1.0.dist-info/entry_points.txt
nbscript-0.1.0.dist-info/top_level.txt
nbscript-0.1.0.dist-info/RECORD
