Metadata-Version: 2.1
Name: nbscript
Version: 0.1.0
Summary: Run Jupyter notebooks like shell scripts
Home-page: https://github.com/NordicHPC/nbscript
Author: Richard Darst
License: UNKNOWN
Platform: UNKNOWN
Classifier: Programming Language :: Python :: 2
Classifier: Programming Language :: Python :: 3
Classifier: License :: OSI Approved :: MIT License
Classifier: Operating System :: OS Independent
Classifier: Development Status :: 3 - Alpha
Classifier: Framework :: Jupyter
Requires-Python: >=2.7, !=3.0.*, !=3.1.*, !=3.2.*, !=3.3.*, !=3.4.*,
Requires-Dist: jupyter-client
Requires-Dist: nbconvert
Requires-Dist: nbformat
